idpet/__init__.py
idpet/bld.bat
idpet/build.sh
idpet/comparison.py
idpet/coord.py
idpet/dimensionality_reduction.py
idpet/ensemble.py
idpet/ensemble_analysis.py
idpet/meta.yaml
idpet/utils.py
idpet/visualization.py
idpet/data/__init__.py
idpet/data/api_client.py
idpet/data/io_utils.py
idpet/data/topology.py
idpet/featurization/__init__.py
idpet/featurization/angles.py
idpet/featurization/distances.py
idpet/featurization/ensemble_level.py
idpet/featurization/glob.py
idpet/featurization/utils.py
idpet-0.1.4.dist-info/METADATA
idpet-0.1.4.dist-info/WHEEL
idpet-0.1.4.dist-info/licenses/LICENSE
idpet-0.1.4.dist-info/RECORD
