Metadata-Version: 2.3
Name: idpet
Version: 0.1.4
Summary: A Python package for analysis of conformational ensembles of intrinsically disordered proteins
Project-URL: Homepage, https://github.com/BioComputingUP/EnsembleTools
Project-URL: Repository, https://github.com/BioComputingUP/EnsembleTools
Author-email: Hamidreza Ghafouri <Hamidreza.ghafouri@studenti.unipd.it>
License: MIT License
Requires-Python: >=3.7
Requires-Dist: matplotlib
Requires-Dist: mdtraj
Requires-Dist: nbformat
Requires-Dist: numba
Requires-Dist: numpy>=1.20
Requires-Dist: pandas
Requires-Dist: plotly
Requires-Dist: requests
Requires-Dist: scikit-learn
Requires-Dist: scipy
Requires-Dist: umap-learn
